outcome/pypicloud_storage_gcs/__init__.py
outcome/pypicloud_storage_gcs/threadsafe_gcs.py
outcome_pypicloud_storage_gcs-0.3.0.dist-info/WHEEL
outcome_pypicloud_storage_gcs-0.3.0.dist-info/METADATA
outcome_pypicloud_storage_gcs-0.3.0.dist-info/RECORD
