Metadata-Version: 2.1
Name: outcome-pypicloud-storage-gcs
Version: 0.3.0
Summary: A fork-safe verion of the GCS Storage backend for PyPICloud.
Home-page: https://github.com/outcome-co/pypicloud-storage-gcs-py
Author: Outcome Engineering
Author-email: engineering@outcome.co
Requires-Python: >=3.8.6,<4.0.0
Classifier: Programming Language :: Python :: 3
Classifier: Programming Language :: Python :: 3.9
Project-URL: Documentation, https://github.com/outcome-co/pypicloud-storage-gcs-py#README
Project-URL: Repository, https://github.com/outcome-co/pypicloud-storage-gcs-py
